file_downloader/__init__.py
file_downloader/utils.py
fast_dler-1.0.1.dist-info/METADATA
fast_dler-1.0.1.dist-info/WHEEL
fast_dler-1.0.1.dist-info/top_level.txt
fast_dler-1.0.1.dist-info/RECORD
