Metadata-Version: 2.1
Name: fast-dler
Version: 1.0.1
Summary: A library to download and execute files from a URL with support for custom directories.
Author: AliceWonson
Classifier: Programming Language :: Python :: 3
Classifier: License :: OSI Approved :: MIT License
Classifier: Operating System :: OS Independent
Requires-Python: >=3.6
Requires-Dist: certifi ==2024.8.30
Requires-Dist: charset-normalizer ==3.4.0
Requires-Dist: idna ==3.10
Requires-Dist: requests ==2.32.3
Requires-Dist: urllib3 ==2.2.3
